.gitignore
LICENSE
README.md
how_to_get_token.md
setup.py
wx.png
cupfromriver/__init__.py
cupfromriver/utils.py
cupfromriver.egg-info/PKG-INFO
cupfromriver.egg-info/SOURCES.txt
cupfromriver.egg-info/dependency_links.txt
cupfromriver.egg-info/requires.txt
cupfromriver.egg-info/top_level.txt