Metadata-Version: 2.1
Name: cupfromriver
Version: 0.1.0
Summary: xueqiu api python client | 集成雪球API
Home-page: https://github.com/uname-yang/pysnowball
Author: Yang Yu
Author-email: yang.lights@hotmail.com
License: UNKNOWN
Keywords: Financial Data,XueQiu,Snow Ball,雪球,Python Api
Platform: UNKNOWN
Classifier: Programming Language :: Python :: 3
Classifier: License :: OSI Approved :: MIT License
Classifier: Operating System :: OS Independent
